setup.py
ml_dwm/__init__.py
ml_dwm.egg-info/PKG-INFO
ml_dwm.egg-info/SOURCES.txt
ml_dwm.egg-info/dependency_links.txt
ml_dwm.egg-info/not-zip-safe
ml_dwm.egg-info/top_level.txt