Metadata-Version: 1.0
Name: ml-dwm
Version: 0.1
Summary: done
Home-page: UNKNOWN
Author: Ankesh
Author-email: ankeshphapale1234@gmail.com
License: MIT
Platform: UNKNOWN
